{
  "ctfidf_model": {
    "bm25_weighting": false,
    "reduce_frequent_words": false
  },
  "vectorizer_model": {
    "params": {
      "analyzer": "word",
      "binary": false,
      "decode_error": "strict",
      "encoding": "utf-8",
      "input": "content",
      "lowercase": true,
      "max_df": 1.0,
      "max_features": null,
      "min_df": 1,
      "ngram_range": [
        1,
        1
      ],
      "stop_words": [
        "anyway",
        "well",
        "us",
        "due",
        "their",
        "would",
        "eight",
        "aren",
        "anywhere",
        "had",
        "own",
        "seems",
        "towards",
        "was",
        "always",
        "call",
        "is",
        "amongst",
        "less",
        "there",
        "at",
        "with",
        "hasn't",
        "been",
        "weren",
        "nothing",
        "ie",
        "during",
        "some",
        "wasnt",
        "be",
        "anyhow",
        "several",
        "more",
        "off",
        "t",
        "four",
        "whatever",
        "beside",
        "that",
        "thereafter",
        "hasnt",
        "next",
        "sometimes",
        "wherein",
        "couldnt",
        "thru",
        "further",
        "since",
        "empty",
        "around",
        "least",
        "onto",
        "when",
        "could",
        "made",
        "but",
        "don",
        "from",
        "whereby",
        "doesn",
        "above",
        "system",
        "any",
        "wouldnt",
        "wasn",
        "sincere",
        "everywhere",
        "m",
        "ll",
        "thus",
        "has",
        "whence",
        "havent",
        "until",
        "twenty",
        "side",
        "up",
        "now",
        "thence",
        "meanwhile",
        "already",
        "inc",
        "wasn't",
        "eleven",
        "then",
        "again",
        "upon",
        "werent",
        "should",
        "either",
        "enough",
        "take",
        "ten",
        "being",
        "because",
        "hereby",
        "the",
        "find",
        "my",
        "somehow",
        "otherwise",
        "in",
        "becomes",
        "formerly",
        "last",
        "cant",
        "although",
        "nor",
        "whenever",
        "yet",
        "down",
        "before",
        "mightn",
        "wouldn't",
        "wouldn",
        "bottom",
        "mine",
        "me",
        "can",
        "every",
        "elsewhere",
        "no",
        "you",
        "noone",
        "two",
        "about",
        "forty",
        "cry",
        "yourself",
        "three",
        "anyone",
        "front",
        "also",
        "ours",
        "didn't",
        "therein",
        "who",
        "alone",
        "of",
        "may",
        "on",
        "ourselves",
        "seeming",
        "were",
        "whether",
        "moreover",
        "get",
        "five",
        "other",
        "doesn't",
        "mustn",
        "across",
        "whereupon",
        "anything",
        "whole",
        "them",
        "him",
        "everything",
        "move",
        "fifteen",
        "throughout",
        "none",
        "wherever",
        "hereupon",
        "done",
        "isn",
        "where",
        "fire",
        "however",
        "ltd",
        "after",
        "so",
        "weren't",
        "becoming",
        "he",
        "nine",
        "yourselves",
        "might",
        "won",
        "why",
        "isn't",
        "can't",
        "hers",
        "shouldnt",
        "we",
        "they",
        "whereafter",
        "isnt",
        "serious",
        "hadnt",
        "latter",
        "through",
        "am",
        "rather",
        "twelve",
        "himself",
        "as",
        "below",
        "few",
        "much",
        "back",
        "within",
        "mustnt",
        "found",
        "fifty",
        "shouldn",
        "first",
        "her",
        "whoever",
        "those",
        "nevertheless",
        "or",
        "co",
        "if",
        "seem",
        "i",
        "whom",
        "keep",
        "others",
        "former",
        "couldn't",
        "itself",
        "therefore",
        "behind",
        "become",
        "along",
        "couldn",
        "except",
        "indeed",
        "thereupon",
        "under",
        "while",
        "never",
        "give",
        "both",
        "via",
        "still",
        "seemed",
        "many",
        "else",
        "mightn't",
        "do",
        "thereby",
        "against",
        "describe",
        "mustn't",
        "hence",
        "one",
        "amoungst",
        "dont",
        "nobody",
        "top",
        "somewhere",
        "together",
        "latterly",
        "even",
        "please",
        "see",
        "re",
        "show",
        "herein",
        "mostly",
        "six",
        "haven't",
        "almost",
        "something",
        "by",
        "thick",
        "hadn't",
        "didn",
        "etc",
        "name",
        "another",
        "un",
        "without",
        "sixty",
        "everyone",
        "myself",
        "thin",
        "beforehand",
        "haven",
        "hadn",
        "besides",
        "into",
        "ever",
        "it",
        "how",
        "out",
        "didnt",
        "for",
        "are",
        "though",
        "afterwards",
        "have",
        "mill",
        "whither",
        "de",
        "hasn",
        "herself",
        "than",
        "once",
        "aren't",
        "a",
        "neither",
        "will",
        "detail",
        "these",
        "must",
        "which",
        "ve",
        "most",
        "con",
        "this",
        "over",
        "put",
        "to",
        "each",
        "too",
        "eg",
        "such",
        "bill",
        "full",
        "your",
        "don't",
        "among",
        "all",
        "our",
        "wont",
        "amount",
        "perhaps",
        "same",
        "arent",
        "mightnt",
        "whose",
        "shouldn't",
        "interest",
        "toward",
        "hereafter",
        "doesnt",
        "whereas",
        "an",
        "often",
        "its",
        "what",
        "themselves",
        "she",
        "hundred",
        "not",
        "sometime",
        "won't",
        "i've",
        "his",
        "between",
        "cannot",
        "and",
        "part",
        "namely",
        "beyond",
        "go",
        "only",
        "fill",
        "nowhere",
        "someone",
        "here",
        "third",
        "yours",
        "very",
        "per",
        "became"
      ],
      "strip_accents": null,
      "token_pattern": "(?u)\\b\\w\\w+\\b",
      "vocabulary": null
    },
    "vocab": {
      "mean": 560,
      "person": 656,
      "unique": 940,
      "things": 896,
      "like": 510,
      "taste": 876,
      "elegant": 295,
      "easy": 283,
      "look": 531,
      "atlisten": 72,
      "means": 562,
      "likes": 514,
      "say": 770,
      "good": 394,
      "usually": 948,
      "tends": 887,
      "appreciate": 47,
      "subtle": 859,
      "details": 250,
      "object": 607,
      "example": 327,
      "fashion": 353,
      "dress": 276,
      "way": 964,
      "elevate": 297,
      "body": 105,
      "features": 358,
      "fabricpatternfit": 346,
      "eccentric": 286,
      "different": 259,
      "think": 897,
      "notice": 602,
      "performance": 655,
      "tiny": 907,
      "writing": 982,
      "multiple": 582,
      "genres": 391,
      "focus": 371,
      "completely": 170,
      "single": 806,
      "diverse": 271,
      "deep": 229,
      "understanding": 934,
      "comparing": 166,
      "music": 584,
      "trust": 926,
      "somebodys": 822,
      "opinion": 624,
      "listen": 522,
      "10": 0,
      "somebody": 821,
      "listens": 524,
      "level": 508,
      "refined": 735,
      "intoxicating": 472,
      "enjoyable": 308,
      "classic": 135,
      "ahead": 28,
      "curve": 221,
      "thoughtful": 900,
      "just": 491,
      "book": 107,
      "bestseller": 101,
      "list": 521,
      "theyve": 893,
      "read": 714,
      "listened": 523,
      "seen": 775,
      "form": 377,
      "make": 544,
      "minds": 570,
      "ability": 1,
      "recognise": 724,
      "nice": 594,
      "art": 55,
      "food": 374,
      "furnishings": 385,
      "expensive": 335,
      "enjoy": 307,
      "increase": 448,
      "ones": 620,
      "knowledge": 498,
      "awareness": 82,
      "basically": 91,
      "closely": 140,
      "shows": 800,
      "new": 592,
      "thats": 890,
      "interesting": 469,
      "range": 713,
      "prefer": 687,
      "enjoys": 311,
      "deeper": 230,
      "simply": 805,
      "puttogether": 705,
      "peices": 650,
      "importantly": 443,
      "understand": 932,
      "sake": 768,
      "told": 908,
      "supposed": 866,
      "humor": 433,
      "technique": 882,
      "quality": 707,
      "similar": 803,
      "tastes": 880,
      "basic": 90,
      "clothing": 143,
      "neutral": 591,
      "colors": 150,
      "foods": 375,
      "strange": 844,
      "tattoos": 881,
      "covering": 200,
      "certain": 121,
      "subjects": 856,
      "current": 220,
      "trendy": 923,
      "nack": 586,
      "finding": 365,
      "value": 951,
      "agree": 26,
      "sense": 781,
      "style": 850,
      "flows": 370,
      "cohesive": 145,
      "clashes": 134,
      "place": 671,
      "applies": 44,
      "decor": 225,
      "forms": 378,
      "media": 564,
      "reasons": 722,
      "entertainment": 312,
      "believe": 97,
      "pretty": 693,
      "idea": 436,
      "popular": 678,
      "looks": 533,
      "referred": 732,
      "makes": 545,
      "terms": 889,
      "appearance": 43,
      "reality": 717,
      "effectively": 291,
      "choices": 129,
      "aligned": 30,
      "consistently": 184,
      "chooses": 131,
      "generally": 390,
      "overall": 636,
      "interests": 470,
      "choose": 130,
      "appealing": 40,
      "nicer": 596,
      "better": 102,
      "option": 628,
      "latest": 503,
      "able": 2,
      "aspects": 67,
      "creative": 208,
      "medium": 565,
      "eminems": 300,
      "lyrical": 541,
      "prowess": 701,
      "personally": 659,
      "fan": 350,
      "tend": 886,
      "books": 108,
      "substance": 858,
      "depth": 242,
      "thoughtprovoking": 901,
      "engage": 306,
      "critical": 210,
      "thinking": 898,
      "literal": 525,
      "eat": 284,
      "healthy": 417,
      "wellprepared": 970,
      "frozen": 380,
      "dinners": 262,
      "junk": 490,
      "actors": 13,
      "awards": 81,
      "picks": 669,
      "objects": 611,
      "unified": 939,
      "picture": 670,
      "people": 651,
      "tastefully": 878,
      "jeans": 481,
      "shirt": 795,
      "based": 89,
      "saying": 771,
      "course": 199,
      "maybe": 558,
      "rich": 756,
      "having": 416,
      "antiques": 38,
      "newly": 593,
      "fancy": 351,
      "clothescars": 142,
      "movie": 580,
      "snob": 812,
      "movies": 581,
      "composed": 175,
      "appreciation": 50,
      "noticing": 603,
      "enjoyment": 310,
      "andor": 35,
      "intellectual": 463,
      "stimulation": 841,
      "comparable": 165,
      "thought": 899,
      "type": 928,
      "spend": 833,
      "time": 904,
      "selective": 779,
      "liking": 516,
      "effort": 292,
      "discovering": 265,
      "knows": 500,
      "correct": 198,
      "talk": 873,
      "sees": 776,
      "horrible": 426,
      "ugly": 931,
      "thing": 895,
      "bad": 84,
      "fine": 366,
      "offensive": 616,
      "admire": 18,
      "pride": 694,
      "thier": 894,
      "surroundings": 867,
      "trendsetters": 922,
      "come": 155,
      "mind": 568,
      "ideas": 437,
      "design": 244,
      "specific": 832,
      "designer": 246,
      "knack": 494,
      "combining": 154,
      "right": 757,
      "creating": 206,
      "figureflattering": 363,
      "use": 946,
      "somewhat": 824,
      "loosely": 534,
      "consuming": 190,
      "blindly": 104,
      "mass": 550,
      "tells": 885,
      "differ": 257,
      "explain": 339,
      "respect": 750,
      "positive": 683,
      "appreciated": 48,
      "creativity": 209,
      "senses": 782,
      "aesthetic": 21,
      "mature": 557,
      "pick": 667,
      "subtler": 860,
      "beauty": 93,
      "world": 980,
      "skill": 809,
      "originality": 630,
      "endures": 304,
      "clothes": 141,
      "appropriate": 51,
      "jobwhether": 482,
      "bar": 86,
      "shoveling": 798,
      "snow": 813,
      "education": 289,
      "intelligence": 464,
      "decipher": 223,
      "difference": 258,
      "higher": 420,
      "lower": 538,
      "appreciates": 49,
      "function": 383,
      "working": 978,
      "harmony": 415,
      "expect": 333,
      "unusual": 943,
      "weird": 968,
      "combinations": 152,
      "normal": 599,
      "relatively": 747,
      "wide": 974,
      "agreement": 27,
      "opinions": 626,
      "visual": 956,
      "outlook": 633,
      "majority": 543,
      "cases": 117,
      "apply": 45,
      "depends": 241,
      "subjective": 855,
      "tell": 884,
      "tale": 871,
      "signs": 802,
      "fits": 369,
      "common": 160,
      "feel": 359,
      "distinguished": 270,
      "masses": 551,
      "express": 340,
      "outside": 635,
      "box": 109,
      "life": 509,
      "judge": 486,
      "eye": 344,
      "arts": 64,
      "asthetic": 71,
      "household": 429,
      "goods": 395,
      "ect": 287,
      "manners": 549,
      "handle": 409,
      "live": 528,
      "communicates": 163,
      "expresses": 341,
      "aesthetically": 22,
      "pleasing": 674,
      "manner": 547,
      "fabric": 345,
      "car": 113,
      "color": 149,
      "comedy": 156,
      "does": 273,
      "include": 446,
      "vulgarity": 961,
      "racism": 712,
      "violence": 955,
      "normally": 600,
      "heshe": 418,
      "consideration": 182,
      "objectionable": 608,
      "talking": 874,
      "carry": 115,
      "public": 702,
      "setting": 789,
      "refers": 734,
      "someones": 823,
      "situations": 808,
      "typically": 930,
      "reasonable": 720,
      "given": 393,
      "topic": 909,
      "logical": 530,
      "understandable": 933,
      "likings": 517,
      "received": 723,
      "population": 679,
      "elitist": 298,
      "sound": 828,
      "ive": 479,
      "associated": 69,
      "cultured": 218,
      "preferences": 689,
      "subdued": 853,
      "cohesiveness": 146,
      "loud": 536,
      "garish": 387,
      "pretentious": 692,
      "easily": 282,
      "influence": 452,
      "lot": 535,
      "smart": 811,
      "knowing": 497,
      "audience": 78,
      "want": 962,
      "follow": 372,
      "modern": 573,
      "trends": 921,
      "study": 847,
      "learned": 506,
      "nowadays": 605,
      "expression": 342,
      "likely": 513,
      "joke": 483,
      "define": 232,
      "consider": 181,
      "likesdislikes": 515,
      "refer": 731,
      "theres": 891,
      "connection": 178,
      "aligns": 31,
      "disliking": 266,
      "know": 496,
      "sort": 827,
      "objectively": 610,
      "laughing": 504,
      "unfunny": 938,
      "comes": 157,
      "funny": 384,
      "personal": 657,
      "bias": 103,
      "true": 925,
      "said": 767,
      "subject": 854,
      "trend": 920,
      "view": 953,
      "grew": 400,
      "areas": 53,
      "itd": 477,
      "luxury": 540,
      "defined": 233,
      "parts": 646,
      "id": 435,
      "perspective": 661,
      "kind": 493,
      "happen": 410,
      "defend": 231,
      "position": 682,
      "indicates": 449,
      "qualities": 706,
      "mirror": 571,
      "intentional": 467,
      "culture": 217,
      "character": 122,
      "materially": 555,
      "perception": 654,
      "matches": 553,
      "commonaverage": 161,
      "rounded": 764,
      "portray": 680,
      "cultures": 219,
      "experiences": 337,
      "stand": 835,
      "confident": 177,
      "opinionated": 625,
      "welljustified": 969,
      "main": 542,
      "determination": 252,
      "really": 718,
      "objective": 609,
      "assume": 70,
      "present": 691,
      "pleasant": 673,
      "coherent": 144,
      "speak": 830,
      "vocabulary": 958,
      "jokes": 484,
      "clever": 139,
      "selection": 777,
      "theyre": 892,
      "perceived": 653,
      "perceive": 652,
      "values": 952,
      "home": 424,
      "entertainments": 313,
      "judgment": 489,
      "individual": 450,
      "response": 753,
      "merely": 566,
      "faddish": 348,
      "moment": 574,
      "seek": 773,
      "bring": 112,
      "attention": 73,
      "selfpromoting": 780,
      "quieter": 711,
      "humble": 432,
      "restrained": 755,
      "egodriven": 293,
      "joking": 485,
      "judging": 488,
      "runs": 765,
      "risk": 758,
      "classism": 136,
      "obviously": 614,
      "degree": 235,
      "referring": 733,
      "properly": 700,
      "mix": 572,
      "match": 552,
      "articles": 57,
      "visually": 957,
      "guess": 403,
      "lives": 529,
      "consume": 187,
      "highly": 421,
      "regarded": 739,
      "caviar": 120,
      "staple": 838,
      "eaten": 285,
      "particularly": 645,
      "kneejerk": 495,
      "phrasing": 664,
      "oh": 618,
      "case": 116,
      "barometer": 87,
      "matter": 556,
      "hand": 408,
      "high": 419,
      "favorable": 357,
      "categories": 118,
      "superior": 865,
      "category": 119,
      "ex": 326,
      "shares": 794,
      "copying": 196,
      "entire": 314,
      "mood": 576,
      "outfit": 632,
      "album": 29,
      "room": 762,
      "space": 829,
      "considered": 183,
      "intention": 466,
      "general": 389,
      "quantity": 708,
      "involves": 475,
      "enjoying": 309,
      "great": 398,
      "dialog": 256,
      "delicious": 236,
      "meal": 559,
      "fast": 355,
      "try": 927,
      "attractive": 77,
      "love": 537,
      "old": 619,
      "rock": 759,
      "roll": 761,
      "overly": 637,
      "brash": 111,
      "timid": 906,
      "emotional": 301,
      "compliment": 172,
      "puts": 703,
      "annoying": 37,
      "irritating": 476,
      "work": 977,
      "including": 447,
      "history": 422,
      "immediately": 440,
      "beautiful": 92,
      "youre": 984,
      "openminded": 623,
      "fully": 381,
      "clear": 138,
      "factors": 347,
      "large": 501,
      "usages": 945,
      "pertaining": 662,
      "consumerism": 188,
      "related": 743,
      "morals": 579,
      "ethically": 322,
      "produced": 696,
      "television": 883,
      "aurally": 79,
      "according": 7,
      "standards": 837,
      "society": 817,
      "sadly": 766,
      "im": 439,
      "whats": 972,
      "lets": 507,
      "song": 825,
      "particular": 644,
      "works": 979,
      "universally": 941,
      "hailed": 406,
      "combination": 151,
      "experience": 336,
      "chef": 124,
      "liked": 512,
      "chocolate": 127,
      "chip": 126,
      "cookies": 194,
      "soft": 819,
      "hard": 412,
      "stuff": 848,
      "rolex": 760,
      "watch": 963,
      "painting": 641,
      "picasso": 666,
      "satisfying": 769,
      "ascribe": 65,
      "decorate": 226,
      "oneself": 621,
      "morally": 578,
      "sophisticated": 826,
      "items": 478,
      "culturally": 216,
      "societally": 816,
      "office": 617,
      "expected": 334,
      "preference": 688,
      "entirely": 315,
      "nearly": 589,
      "believes": 98,
      "question": 709,
      "discerning": 263,
      "knowledgeable": 499,
      "artmusicliterature": 63,
      "admit": 19,
      "share": 792,
      "involved": 474,
      "tracings": 911,
      "recognition": 725,
      "painter": 640,
      "feelings": 361,
      "tries": 924,
      "relative": 746,
      "term": 888,
      "appeals": 41,
      "reason": 719,
      "appeal": 39,
      "observer": 612,
      "base": 88,
      "esthetic": 319,
      "guided": 404,
      "superficiality": 863,
      "wholesome": 973,
      "degrading": 234,
      "finer": 367,
      "relates": 744,
      "socioeconomic": 818,
      "status": 839,
      "addition": 15,
      "educated": 288,
      "represented": 748,
      "simple": 804,
      "understated": 936,
      "film": 364,
      "literature": 526,
      "story": 843,
      "allows": 33,
      "reader": 715,
      "viewer": 954,
      "participate": 643,
      "determining": 253,
      "meaning": 561,
      "pertains": 663,
      "preach": 686,
      "hyperbolic": 434,
      "lines": 519,
      "harmonious": 414,
      "persons": 660,
      "judgement": 487,
      "poor": 677,
      "ages": 25,
      "quiet": 710,
      "solid": 820,
      "bold": 106,
      "seeking": 774,
      "embarrass": 299,
      "furniture": 386,
      "comfortable": 158,
      "sturdy": 849,
      "action": 12,
      "polite": 676,
      "respective": 752,
      "sensibility": 783,
      "acquired": 11,
      "earned": 281,
      "university": 942,
      "college": 148,
      "reflects": 738,
      "commonly": 162,
      "understood": 937,
      "descriptions": 243,
      "set": 788,
      "asked": 66,
      "accepted": 4,
      "extent": 343,
      "complements": 169,
      "environment": 316,
      "offend": 615,
      "induce": 451,
      "envy": 317,
      "desire": 249,
      "designed": 245,
      "care": 114,
      "finished": 368,
      "nicely": 595,
      "demonstrates": 238,
      "discernment": 264,
      "travel": 917,
      "culinary": 213,
      "reserve": 749,
      "vulgar": 960,
      "crass": 203,
      "holds": 423,
      "standard": 836,
      "behavior": 96,
      "spending": 834,
      "little": 527,
      "money": 575,
      "appear": 42,
      "contains": 192,
      "ingredients": 456,
      "created": 205,
      "craftmanship": 201,
      "evaluation": 323,
      "acknowledges": 10,
      "refinement": 736,
      "utility": 949,
      "elegance": 294,
      "regards": 741,
      "consumption": 191,
      "feeling": 360,
      "talks": 875,
      "dresses": 278,
      "compatible": 167,
      "distinguish": 269,
      "professional": 697,
      "area": 52,
      "wear": 967,
      "appreciable": 46,
      "stylish": 852,
      "ways": 965,
      "complement": 168,
      "interesttaste": 471,
      "elements": 296,
      "chosen": 133,
      "plot": 675,
      "dispensing": 267,
      "educational": 290,
      "information": 454,
      "murder": 583,
      "mysteries": 585,
      "detective": 251,
      "superhero": 864,
      "examples": 328,
      "documentaries": 272,
      "geology": 392,
      "animals": 36,
      "lowest": 539,
      "denominator": 240,
      "exceptional": 329,
      "rothkos": 763,
      "whartons": 971,
      "novels": 604,
      "combine": 153,
      "critically": 211,
      "acclaimed": 5,
      "intelligent": 465,
      "vrry": 959,
      "insightful": 458,
      "pairing": 642,
      "cultivated": 214,
      "sensible": 784,
      "millions": 567,
      "cultural": 215,
      "obvious": 613,
      "passive": 649,
      "reflect": 737,
      "lazy": 505,
      "attitude": 75,
      "humanity": 430,
      "following": 373,
      "identify": 438,
      "shared": 793,
      "group": 402,
      "community": 164,
      "promote": 699,
      "constructive": 186,
      "behaving": 95,
      "shove": 797,
      "consumers": 189,
      "throat": 902,
      "table": 868,
      "decorated": 227,
      "timeless": 905,
      "trashy": 916,
      "gaudy": 388,
      "forced": 376,
      "complimentary": 173,
      "belongs": 99,
      "selections": 778,
      "line": 518,
      "styles": 851,
      "traditional": 912,
      "contemporary": 193,
      "overthetop": 638,
      "chose": 132,
      "ordinary": 629,
      "tasteful": 877,
      "gross": 401,
      "childish": 125,
      "inappropriate": 444,
      "shades": 791,
      "subtleties": 861,
      "nonviolent": 598,
      "subset": 857,
      "humans": 431,
      "artistic": 60,
      "informed": 455,
      "adventurous": 20,
      "worthy": 981,
      "actually": 14,
      "takes": 870,
      "talent": 872,
      "create": 204,
      "coincided": 147,
      "instance": 462,
      "jarring": 480,
      "overwhelming": 639,
      "enduring": 305,
      "significance": 801,
      "affinity": 24,
      "natural": 588,
      "developed": 254,
      "widely": 975,
      "domain": 275,
      "favor": 356,
      "transcends": 915,
      "passing": 648,
      "fads": 349,
      "exemplariness": 331,
      "devoid": 255,
      "instagram": 461,
      "influencers": 453,
      "youtube": 985,
      "personalities": 658,
      "fun": 382,
      "exciting": 330,
      "likeable": 511,
      "types": 929,
      "artists": 62,
      "haha": 405,
      "picking": 668,
      "displaying": 268,
      "serving": 787,
      "yes": 983,
      "recommendation": 729,
      "recommend": 728,
      "accomplishment": 6,
      "creation": 207,
      "complexity": 171,
      "demonstrate": 237,
      "sensitivity": 785,
      "aesthetics": 23,
      "admiration": 17,
      "recognize": 726,
      "drive": 279,
      "choice": 128,
      "acknowledge": 8,
      "transcend": 914,
      "artistically": 61,
      "acknowledged": 9,
      "showing": 799,
      "uplift": 944,
      "inspire": 459,
      "hair": 407,
      "oposite": 627,
      "sex": 790,
      "prefers": 690,
      "constructed": 185,
      "structure": 846,
      "field": 362,
      "greatly": 399,
      "impacted": 441,
      "regardless": 740,
      "allow": 32,
      "endeavors": 303,
      "ear": 280,
      "concerning": 176,
      "experiment": 338,
      "doing": 274,
      "house": 428,
      "cool": 195,
      "decisions": 224,
      "decorating": 228,
      "balls": 85,
      "conservative": 180,
      "artist": 59,
      "relate": 742,
      "profound": 698,
      "graceful": 397,
      "eternal": 320,
      "charm": 123,
      "power": 685,
      "attract": 76,
      "best": 100,
      "situation": 807,
      "restaurants": 754,
      "recommends": 730,
      "articulate": 58,
      "differs": 260,
      "possibilites": 684,
      "socially": 815,
      "clean": 137,
      "ba": 83,
      "keeping": 492,
      "social": 814,
      "norms": 601,
      "moral": 577,
      "relational": 745,
      "component": 174,
      "dating": 222,
      "eventually": 324,
      "friends": 379,
      "dressed": 277,
      "far": 352,
      "woman": 976,
      "pic": 665,
      "man": 546,
      "acceptable": 3,
      "attire": 74,
      "behaves": 94,
      "services": 786,
      "used": 947,
      "desirable": 248,
      "nails": 587,
      "sloppy": 810,
      "intrinsically": 473,
      "valuable": 950,
      "interact": 468,
      "exhibitionists": 332,
      "implies": 442,
      "avoid": 80,
      "crude": 212,
      "reasoning": 721,
      "coral": 197,
      "lipstick": 520,
      "nonbourgeoisiegentrified": 597,
      "traditionalorthodox": 913,
      "inspired": 460,
      "schoolbaroque": 772,
      "gothic": 396,
      "shopping": 796,
      "matching": 554,
      "tacky": 869,
      "fashions": 354,
      "strong": 845,
      "principles": 695,
      "speaks": 831,
      "evokes": 325,
      "emotions": 302,
      "craftsmanship": 202,
      "demonstration": 239,
      "putting": 704,
      "hosting": 427,
      "dinner": 261,
      "party": 647,
      "insight": 457,
      "analyzed": 34,
      "branch": 110,
      "places": 672,
      "real": 716,
      "outrageous": 634,
      "looked": 532,
      "admirable": 16,
      "posessions": 681,
      "designing": 247,
      "arrangement": 54,
      "artfurniture": 56,
      "open": 622,
      "minded": 569,
      "nuance": 606,
      "subtlety": 862,
      "understands": 935,
      "necessarily": 590,
      "tied": 903,
      "commerce": 159,
      "inclined": 445,
      "mannerisms": 548,
      "connoisseur": 179,
      "recognized": 727,
      "tastefulness": 879,
      "ornate": 631,
      "respectful": 751,
      "honest": 425,
      "topics": 910,
      "associate": 68,
      "ethical": 321,
      "hardworking": 413,
      "wealth": 966,
      "stepping": 840,
      "stonesomeone": 842,
      "treats": 919,
      "treated": 918,
      "lasting": 502,
      "ephemeral": 318,
      "measure": 563,
      "happiness": 411
    }
  }
}