{
  "topic_representations": {
    "-1": [
      [
        "good",
        0.10572975066694203
      ],
      [
        "person",
        0.1025175881072973
      ],
      [
        "taste",
        0.09182287286198337
      ],
      [
        "think",
        0.07753555330626488
      ],
      [
        "fashion",
        0.07577579257649282
      ],
      [
        "like",
        0.06598367120105418
      ],
      [
        "means",
        0.06463268758988118
      ],
      [
        "art",
        0.05651217648200704
      ],
      [
        "things",
        0.05216071735329886
      ],
      [
        "mean",
        0.04600667844034842
      ]
    ],
    "0": [
      [
        "taste",
        0.1635594922854079
      ],
      [
        "good",
        0.15403730916132072
      ],
      [
        "person",
        0.06869321146688025
      ],
      [
        "like",
        0.062144104126854914
      ],
      [
        "things",
        0.06122888804259364
      ],
      [
        "think",
        0.058736523679207134
      ],
      [
        "people",
        0.051558248773395245
      ],
      [
        "say",
        0.05041749427564257
      ],
      [
        "mean",
        0.043329565686276425
      ],
      [
        "usually",
        0.03508645874109796
      ]
    ],
    "1": [
      [
        "like",
        0.1043462707365508
      ],
      [
        "things",
        0.08733887556831436
      ],
      [
        "good",
        0.07454141540288692
      ],
      [
        "art",
        0.06728891711345955
      ],
      [
        "choices",
        0.06642115903470458
      ],
      [
        "means",
        0.05611520162842397
      ],
      [
        "appreciate",
        0.05218805352726789
      ],
      [
        "look",
        0.048644507219755585
      ],
      [
        "taste",
        0.04270831295906204
      ],
      [
        "appealing",
        0.041857331907411754
      ]
    ]
  },
  "topics": [
    -1,
    0,
    0,
    1,
    1,
    0,
    1,
    1,
    -1,
    0,
    0,
    -1,
    -1,
    0,
    0,
    0,
    1,
    1,
    0,
    -1,
    1,
    0,
    -1,
    0,
    0,
    1,
    1,
    0,
    0,
    1,
    0,
    0,
    0,
    -1,
    0,
    1,
    1,
    0,
    0,
    -1,
    0,
    0,
    0,
    0,
    -1,
    0,
    0,
    -1,
    0,
    -1,
    0,
    0,
    -1,
    0,
    -1,
    0,
    1,
    -1,
    1,
    0,
    1,
    0,
    1,
    1,
    0,
    1,
    1,
    0,
    0,
    1,
    1,
    0,
    0,
    0,
    0,
    1,
    1,
    0,
    -1,
    0,
    0,
    0,
    0,
    1,
    0,
    0,
    1,
    1,
    0,
    0,
    0,
    0,
    1,
    0,
    0,
    1,
    0,
    0,
    1,
    0,
    0,
    1,
    0,
    1,
    0,
    0,
    -1,
    1,
    1,
    0,
    1,
    1,
    0,
    0,
    1,
    1,
    1,
    1,
    1,
    1,
    1,
    0,
    1,
    0,
    0,
    1,
    0,
    0,
    1,
    0,
    0,
    1,
    1,
    1,
    1,
    1,
    0,
    1,
    0,
    1,
    0,
    0,
    0,
    0,
    0,
    0,
    0,
    0,
    1,
    1,
    1,
    -1,
    1,
    0,
    0,
    0,
    0,
    0,
    0,
    1,
    1,
    0,
    1,
    1,
    1,
    1,
    0,
    0,
    1,
    -1,
    0,
    1,
    -1,
    1,
    -1,
    1,
    0,
    0,
    1,
    1,
    1,
    0,
    0,
    1,
    0,
    0,
    0,
    1,
    0,
    0,
    1,
    0,
    1,
    1,
    0,
    -1,
    1,
    1,
    1,
    1,
    0,
    0,
    0,
    0,
    0,
    1,
    0,
    1,
    0,
    0,
    0,
    1,
    1,
    0,
    0,
    0,
    -1,
    1,
    0,
    0,
    1,
    1,
    1,
    0
  ],
  "topic_sizes": {
    "-1": 22,
    "0": 116,
    "1": 86
  },
  "topic_mapper": [
    [
      -1,
      -1,
      -1
    ],
    [
      0,
      0,
      1
    ],
    [
      1,
      1,
      0
    ]
  ],
  "topic_labels": {
    "-1": "-1_good_person_taste_think",
    "0": "0_taste_good_person_like",
    "1": "1_like_things_good_art"
  },
  "custom_labels": null,
  "_outliers": 1,
  "topic_aspects": {}
}